protobuf_init/__init__.py
protobuf_init/plugin.py
protobuf_init-0.3.0.dist-info/entry_points.txt
protobuf_init-0.3.0.dist-info/LICENSE.txt
protobuf_init-0.3.0.dist-info/WHEEL
protobuf_init-0.3.0.dist-info/METADATA
protobuf_init-0.3.0.dist-info/RECORD
