Metadata-Version: 2.1
Name: protobuf-init
Version: 0.3.0
Summary: generate __init__.py files for protobuf projects
Home-page: https://github.com/crflynn/protobuf-init
License: MIT
Keywords: protobuf,protocol,buffers,protoc,plugin
Author: flynn
Author-email: crf204@gmail.com
Requires-Python: >=3.8
Classifier: Development Status :: 4 - Beta
Classifier: License :: OSI Approved :: MIT License
Classifier: Programming Language :: Python
Classifier: Programming Language :: Python :: 3
Classifier: Programming Language :: Python :: 3.10
Classifier: Programming Language :: Python :: 3.8
Classifier: Programming Language :: Python :: 3.9
Requires-Dist: protobuf (>=3.19.1)
Project-URL: Documentation, https://github.com/crflynn/protobuf-init
Project-URL: Repository, https://github.com/crflynn/protobuf-init
